django_include_bootstrap/__init__.py
django_include_bootstrap/static/css/bootstrap-grid.css
django_include_bootstrap/static/css/bootstrap-grid.css.map
django_include_bootstrap/static/css/bootstrap-grid.min.css
django_include_bootstrap/static/css/bootstrap-grid.min.css.map
django_include_bootstrap/static/css/bootstrap-grid.rtl.css
django_include_bootstrap/static/css/bootstrap-grid.rtl.css.map
django_include_bootstrap/static/css/bootstrap-grid.rtl.min.css
django_include_bootstrap/static/css/bootstrap-grid.rtl.min.css.map
django_include_bootstrap/static/css/bootstrap-reboot.css
django_include_bootstrap/static/css/bootstrap-reboot.css.map
django_include_bootstrap/static/css/bootstrap-reboot.min.css
django_include_bootstrap/static/css/bootstrap-reboot.min.css.map
django_include_bootstrap/static/css/bootstrap-reboot.rtl.css
django_include_bootstrap/static/css/bootstrap-reboot.rtl.css.map
django_include_bootstrap/static/css/bootstrap-reboot.rtl.min.css
django_include_bootstrap/static/css/bootstrap-reboot.rtl.min.css.map
django_include_bootstrap/static/css/bootstrap-utilities.css
django_include_bootstrap/static/css/bootstrap-utilities.css.map
django_include_bootstrap/static/css/bootstrap-utilities.min.css
django_include_bootstrap/static/css/bootstrap-utilities.min.css.map
django_include_bootstrap/static/css/bootstrap-utilities.rtl.css
django_include_bootstrap/static/css/bootstrap-utilities.rtl.css.map
django_include_bootstrap/static/css/bootstrap-utilities.rtl.min.css
django_include_bootstrap/static/css/bootstrap-utilities.rtl.min.css.map
django_include_bootstrap/static/css/bootstrap.css
django_include_bootstrap/static/css/bootstrap.css.map
django_include_bootstrap/static/css/bootstrap.min.css
django_include_bootstrap/static/css/bootstrap.min.css.map
django_include_bootstrap/static/css/bootstrap.rtl.css
django_include_bootstrap/static/css/bootstrap.rtl.css.map
django_include_bootstrap/static/css/bootstrap.rtl.min.css
django_include_bootstrap-5.3.8.1.dist-info/METADATA
django_include_bootstrap-5.3.8.1.dist-info/WHEEL
django_include_bootstrap-5.3.8.1.dist-info/top_level.txt
django_include_bootstrap-5.3.8.1.dist-info/RECORD
